{
	"editor": {
		"allAngles": true,
		"entityTextureMode": false
	},
	"textureWidth": 16,
	"textureHeight": 16,
	"textureSizes": {
	},
	"textures": {
		"livermushroom": "block/plant/mushroom/livermushroom/livermushroom",
		"pores": "block/plant/mushroom/pores"
	},
	"elements": [
		{
			"name": "origin",
			"from": [ 8.0, 0.0, 8.0 ], 
			"to": [ 8.0, 0.0, 8.0 ], 
			"rotationOrigin": [ 8.0, 0.0, 8.0 ],
			"faces": {
				"north": { "texture": "#livermushroom", "uv": [ 0.0, 0.0, 0.5, 0.5 ], "enabled": false },
				"east": { "texture": "#livermushroom", "uv": [ 0.0, 0.0, 0.5, 0.5 ], "enabled": false },
				"south": { "texture": "#livermushroom", "uv": [ 0.0, 0.0, 0.5, 0.5 ], "enabled": false },
				"west": { "texture": "#livermushroom", "uv": [ 0.0, 0.0, 0.5, 0.5 ], "enabled": false },
				"up": { "texture": "#livermushroom", "uv": [ 0.0, 0.0, 0.5, 0.5 ], "enabled": false },
				"down": { "texture": "#livermushroom", "uv": [ 0.0, 0.0, 0.5, 0.5 ], "enabled": false }
			},
			"children": [
				{
					"name": "tiny",
					"from": [ 2.3, 2.7, 8.0 ], 
					"to": [ 2.7, 3.7, 8.4 ], 
					"rotationOrigin": [ 2.5, 2.7, 8.2 ],
					"rotationX": -53.0,
					"rotationY": -32.0,
					"rotationZ": 6.0,
					"faces": {
						"north": { "texture": "#livermushroom", "uv": [ 13.0, 14.5, 13.5, 15.5 ] },
						"east": { "texture": "#livermushroom", "uv": [ 11.0, 12.5, 11.5, 13.5 ] },
						"south": { "texture": "#livermushroom", "uv": [ 9.5, 13.5, 10.0, 14.5 ] },
						"west": { "texture": "#livermushroom", "uv": [ 10.5, 13.0, 11.0, 14.0 ] },
						"up": { "texture": "#livermushroom", "uv": [ 11.0, 11.0, 11.5, 11.5 ], "windMode": [-1,-1,-1,-1] },
						"down": { "texture": "#livermushroom", "uv": [ 10.5, 14.0, 11.0, 14.5 ] }
					}
				},
				{
					"name": "tiny14",
					"from": [ 4.3, 7.0, 8.0 ], 
					"to": [ 4.7, 7.5, 8.4 ], 
					"rotationOrigin": [ 4.5, 7.0, 8.2 ],
					"rotationX": -72.0,
					"rotationY": -18.0,
					"faces": {
						"north": { "texture": "#livermushroom", "uv": [ 10.0, 13.0, 10.5, 13.5 ] },
						"east": { "texture": "#livermushroom", "uv": [ 12.0, 12.5, 12.5, 13.0 ] },
						"south": { "texture": "#livermushroom", "uv": [ 9.0, 11.5, 9.5, 12.0 ] },
						"west": { "texture": "#livermushroom", "uv": [ 9.0, 10.5, 9.5, 11.0 ] },
						"up": { "texture": "#livermushroom", "uv": [ 10.0, 9.5, 10.5, 10.0 ], "windMode": [-1,-1,-1,-1] },
						"down": { "texture": "#livermushroom", "uv": [ 11.5, 14.5, 12.0, 15.0 ] }
					}
				},
				{
					"name": "single voxel",
					"from": [ 4.0, 12.0, 7.1 ], 
					"to": [ 5.0, 12.5, 8.1 ], 
					"rotationOrigin": [ 4.5, 12.0, 7.6 ],
					"rotationX": -36.0,
					"rotationY": 33.0,
					"faces": {
						"north": { "texture": "#livermushroom", "uv": [ 3.0, 14.5, 4.0, 15.0 ] },
						"east": { "texture": "#livermushroom", "uv": [ 5.0, 14.5, 6.0, 15.0 ] },
						"south": { "texture": "#livermushroom", "uv": [ 4.0, 14.0, 5.0, 14.5 ] },
						"west": { "texture": "#livermushroom", "uv": [ 2.5, 13.5, 3.5, 14.0 ] },
						"up": { "texture": "#livermushroom", "uv": [ 3.0, 11.0, 4.0, 12.0 ] },
						"down": { "texture": "#pores", "uv": [ 5.0, 2.0, 6.0, 3.0 ] }
					}
				},
				{
					"name": "tiny18",
					"from": [ -4.7, 14.0, 7.9 ], 
					"to": [ -4.3, 15.0, 8.3 ], 
					"rotationOrigin": [ -4.5, 14.0, 8.1 ],
					"rotationX": -67.0,
					"rotationY": -62.0,
					"rotationZ": 3.0,
					"faces": {
						"north": { "texture": "#livermushroom", "uv": [ 8.5, 12.5, 9.0, 13.5 ] },
						"east": { "texture": "#livermushroom", "uv": [ 11.5, 14.0, 12.0, 15.0 ] },
						"south": { "texture": "#livermushroom", "uv": [ 10.5, 11.0, 11.0, 12.0 ] },
						"west": { "texture": "#livermushroom", "uv": [ 9.5, 10.5, 10.0, 11.5 ] },
						"up": { "texture": "#livermushroom", "uv": [ 10.5, 9.5, 11.0, 10.0 ], "windMode": [-1,-1,-1,-1] },
						"down": { "texture": "#livermushroom", "uv": [ 11.0, 13.5, 11.5, 14.0 ] }
					}
				},
				{
					"name": "tiny21",
					"from": [ 5.3, 0.4, 7.9 ], 
					"to": [ 5.7, 0.9, 8.3 ], 
					"rotationOrigin": [ 5.5, 0.4, 8.1 ],
					"rotationX": -44.0,
					"rotationY": 13.0,
					"faces": {
						"north": { "texture": "#livermushroom", "uv": [ 12.5, 12.0, 13.0, 12.5 ] },
						"east": { "texture": "#livermushroom", "uv": [ 13.5, 13.5, 14.0, 14.0 ] },
						"south": { "texture": "#livermushroom", "uv": [ 9.0, 13.0, 9.5, 13.5 ] },
						"west": { "texture": "#livermushroom", "uv": [ 10.0, 12.0, 10.5, 12.5 ] },
						"up": { "texture": "#livermushroom", "uv": [ 10.5, 12.5, 11.0, 13.0 ], "windMode": [-1,-1,-1,-1] },
						"down": { "texture": "#livermushroom", "uv": [ 13.5, 14.0, 14.0, 14.5 ] }
					}
				},
				{
					"name": "medium stalk",
					"from": [ -5.95, 6.9, 7.98 ], 
					"to": [ -5.35, 7.4, 8.58 ], 
					"rotationOrigin": [ -5.6509, 6.9, 8.2763 ],
					"rotationX": -69.0,
					"rotationY": -22.0,
					"rotationZ": -5.0,
					"faces": {
						"north": { "texture": "#livermushroom", "uv": [ 10.0, 13.5, 10.5, 14.0 ] },
						"east": { "texture": "#livermushroom", "uv": [ 11.5, 13.5, 12.0, 14.0 ] },
						"south": { "texture": "#livermushroom", "uv": [ 11.0, 13.5, 11.5, 14.0 ] },
						"west": { "texture": "#livermushroom", "uv": [ 12.0, 12.0, 12.5, 12.5 ] },
						"up": { "texture": "#livermushroom", "uv": [ 11.0, 9.5, 11.5, 10.0 ], "windMode": [-1,-1,-1,-1] },
						"down": { "texture": "#livermushroom", "uv": [ 11.5, 14.5, 12.0, 15.0 ] }
					}
				},
				{
					"name": "medium small2",
					"from": [ -2.65, 0.8, 8.02 ], 
					"to": [ -2.05, 1.3, 8.62 ], 
					"rotationOrigin": [ -2.3491, 0.8, 8.3237 ],
					"rotationX": -80.0,
					"rotationY": -22.0,
					"rotationZ": -6.0,
					"faces": {
						"north": { "texture": "#livermushroom", "uv": [ 15.0, 14.0, 15.5, 14.5 ] },
						"east": { "texture": "#livermushroom", "uv": [ 12.5, 14.0, 13.0, 14.5 ] },
						"south": { "texture": "#livermushroom", "uv": [ 9.5, 13.0, 10.0, 13.5 ] },
						"west": { "texture": "#livermushroom", "uv": [ 11.5, 12.0, 12.0, 12.5 ] },
						"up": { "texture": "#livermushroom", "uv": [ 10.0, 10.5, 10.5, 11.0 ], "windMode": [-1,-1,-1,-1] },
						"down": { "texture": "#livermushroom", "uv": [ 12.0, 14.0, 12.5, 14.5 ] }
					}
				},
				{
					"name": "medium small",
					"from": [ 0.2, 8.9, 8.2 ], 
					"to": [ 0.8, 9.9, 8.8 ], 
					"rotationOrigin": [ 0.5, 8.9, 8.5 ],
					"rotationX": -65.0,
					"rotationY": 16.0,
					"rotationZ": -4.0,
					"faces": {
						"north": { "texture": "#livermushroom", "uv": [ 11.5, 12.0, 12.0, 13.0 ] },
						"east": { "texture": "#livermushroom", "uv": [ 13.0, 13.5, 13.5, 14.5 ] },
						"south": { "texture": "#livermushroom", "uv": [ 10.5, 13.5, 11.0, 14.5 ] },
						"west": { "texture": "#livermushroom", "uv": [ 10.0, 14.0, 10.5, 15.0 ] },
						"up": { "texture": "#livermushroom", "uv": [ 9.5, 11.0, 10.0, 11.5 ], "windMode": [-1,-1,-1,-1] },
						"down": { "texture": "#livermushroom", "uv": [ 11.0, 14.5, 11.5, 15.0 ] }
					}
				},
				{
					"name": "tiny20",
					"from": [ 0.09, 14.0, 7.96 ], 
					"to": [ 0.49, 14.5, 8.36 ], 
					"rotationOrigin": [ 0.1856, 14.0, 8.1631 ],
					"rotationX": -72.0,
					"rotationY": 16.0,
					"faces": {
						"north": { "texture": "#livermushroom", "uv": [ 13.5, 13.0, 14.0, 13.5 ] },
						"east": { "texture": "#livermushroom", "uv": [ 13.0, 13.0, 13.5, 13.5 ] },
						"south": { "texture": "#livermushroom", "uv": [ 9.5, 12.5, 10.0, 13.0 ] },
						"west": { "texture": "#livermushroom", "uv": [ 9.0, 9.0, 9.5, 9.5 ] },
						"up": { "texture": "#livermushroom", "uv": [ 11.0, 11.0, 11.5, 11.5 ], "windMode": [-1,-1,-1,-1] },
						"down": { "texture": "#livermushroom", "uv": [ 11.0, 14.5, 11.5, 15.0 ] }
					}
				}
			]
		}
	]}