{
	"editor": {
		"allAngles": true,
		"entityTextureMode": false
	},
	"textureWidth": 16,
	"textureHeight": 16,
	"textureSizes": {
	},
	"textures": {
		"normal1-6": "block/plant/crop/sunflower/normal1-6"
	},
	"elements": [
		{
			"name": "origin",
			"from": [ 8.0, 0.0, 8.0 ], 
			"to": [ 8.0, 0.0, 8.0 ], 
			"rotationOrigin": [ 8.0, 0.0, 8.0 ],
			"foliageWaveSpecial": 3, "faces": {
				"north": { "texture": "#normal1-6", "uv": [ 0.0, 0.0, 0.5, 0.5 ], "enabled": false },
				"east": { "texture": "#normal1-6", "uv": [ 0.0, 0.0, 0.5, 0.5 ], "enabled": false },
				"south": { "texture": "#normal1-6", "uv": [ 0.0, 0.0, 0.5, 0.5 ], "enabled": false },
				"west": { "texture": "#normal1-6", "uv": [ 0.0, 0.0, 0.5, 0.5 ], "enabled": false },
				"up": { "texture": "#normal1-6", "uv": [ 0.0, 0.0, 0.5, 0.5 ], "enabled": false },
				"down": { "texture": "#normal1-6", "uv": [ 0.0, 0.0, 0.5, 0.5 ], "enabled": false }
			},
			"children": [
				{
					"name": "stemdown",
					"from": [ -4.1, -0.1, -4.1 ], 
					"to": [ -3.8, 3.9, -3.8 ], 
					"rotationOrigin": [ -4.0, -0.1, -4.0 ],
					"rotationY": -45.0,
					"foliageWaveSpecial": 3, "faces": {
						"north": { "texture": "#normal1-6", "uv": [ 0.0, 0.0, 0.5, 4.0 ] },
						"east": { "texture": "#normal1-6", "uv": [ 0.0, 0.0, 0.5, 4.0 ] },
						"south": { "texture": "#normal1-6", "uv": [ 1.0, 0.0, 1.5, 4.0 ] },
						"west": { "texture": "#normal1-6", "uv": [ 0.0, 0.0, 0.5, 4.0 ] },
						"up": { "texture": "#normal1-6", "uv": [ 0.0, 0.0, 0.5, 0.5 ] },
						"down": { "texture": "#normal1-6", "uv": [ 0.5, 14.5, 1.0, 15.0 ] }
					},
					"children": [
						{
							"name": "Leaf1",
							"from": [ -1.2, 2.0, -1.3 ], 
							"to": [ 1.3, 2.0, 0.2 ], 
							"rotationOrigin": [ 0.1, 2.0, 0.2 ],
							"rotationX": 6.0,
							"foliageWaveSpecial": 3, "faces": {
								"north": { "texture": "#normal1-6", "uv": [ 0.0, 0.0, 2.5, 0.5 ], "enabled": false },
								"east": { "texture": "#normal1-6", "uv": [ 0.0, 0.0, 1.5, 0.5 ], "enabled": false },
								"south": { "texture": "#normal1-6", "uv": [ 0.0, 0.0, 2.5, 0.5 ], "enabled": false },
								"west": { "texture": "#normal1-6", "uv": [ 0.0, 0.0, 1.5, 0.5 ], "enabled": false },
								"up": { "texture": "#normal1-6", "uv": [ 13.5, 13.5, 16.0, 15.0 ] },
								"down": { "texture": "#normal1-6", "uv": [ 0.0, 0.0, 2.5, 1.5 ], "enabled": false }
							}
						},
						{
							"name": "Leaf3",
							"from": [ -1.2, 1.0, -1.3 ], 
							"to": [ 1.3, 1.0, 0.2 ], 
							"rotationOrigin": [ 0.1, 1.0, 0.2 ],
							"rotationX": -25.0,
							"rotationY": -157.5,
							"foliageWaveSpecial": 3, "faces": {
								"north": { "texture": "#normal1-6", "uv": [ 0.0, 0.0, 2.5, 0.5 ], "enabled": false },
								"east": { "texture": "#normal1-6", "uv": [ 0.0, 0.0, 1.5, 0.5 ], "enabled": false },
								"south": { "texture": "#normal1-6", "uv": [ 0.0, 0.0, 2.5, 0.5 ], "enabled": false },
								"west": { "texture": "#normal1-6", "uv": [ 0.0, 0.0, 1.5, 0.5 ], "enabled": false },
								"up": { "texture": "#normal1-6", "uv": [ 13.5, 13.5, 16.0, 15.0 ] },
								"down": { "texture": "#normal1-6", "uv": [ 0.0, 0.0, 2.5, 1.5 ], "enabled": false }
							}
						},
						{
							"name": "Leaf4",
							"from": [ -1.4, 3.0, -1.1 ], 
							"to": [ 1.1, 3.0, 0.4 ], 
							"rotationOrigin": [ -0.2, 3.0, 0.4 ],
							"rotationX": -3.0,
							"rotationY": 135.0,
							"rotationZ": -22.5,
							"foliageWaveSpecial": 3, "faces": {
								"north": { "texture": "#normal1-6", "uv": [ 0.0, 0.0, 2.5, 0.5 ], "enabled": false },
								"east": { "texture": "#normal1-6", "uv": [ 0.0, 0.0, 1.5, 0.5 ], "enabled": false },
								"south": { "texture": "#normal1-6", "uv": [ 0.0, 0.0, 2.5, 0.5 ], "enabled": false },
								"west": { "texture": "#normal1-6", "uv": [ 0.0, 0.0, 1.5, 0.5 ], "enabled": false },
								"up": { "texture": "#normal1-6", "uv": [ 13.5, 13.5, 16.0, 15.0 ] },
								"down": { "texture": "#normal1-6", "uv": [ 0.0, 0.0, 2.5, 1.5 ], "enabled": false }
							}
						},
						{
							"name": "Leaf5",
							"from": [ -1.2, 3.4, -1.2 ], 
							"to": [ 1.3, 3.4, 0.3 ], 
							"rotationOrigin": [ 0.1, 3.4, 0.3 ],
							"rotationX": -19.0,
							"rotationY": -135.0,
							"rotationZ": -6.0,
							"foliageWaveSpecial": 3, "faces": {
								"north": { "texture": "#normal1-6", "uv": [ 0.0, 0.0, 2.5, 0.5 ], "enabled": false },
								"east": { "texture": "#normal1-6", "uv": [ 0.0, 0.0, 1.5, 0.5 ], "enabled": false },
								"south": { "texture": "#normal1-6", "uv": [ 0.0, 0.0, 2.5, 0.5 ], "enabled": false },
								"west": { "texture": "#normal1-6", "uv": [ 0.0, 0.0, 1.5, 0.5 ], "enabled": false },
								"up": { "texture": "#normal1-6", "uv": [ 13.5, 13.5, 16.0, 15.0 ] },
								"down": { "texture": "#normal1-6", "uv": [ 0.0, 0.0, 2.5, 1.5 ], "enabled": false }
							}
						},
						{
							"name": "Leaf6",
							"from": [ -1.3, 3.8, -1.3 ], 
							"to": [ 1.2, 3.8, 0.2 ], 
							"rotationOrigin": [ 0.0, 3.8, 0.2 ],
							"rotationX": 25.0,
							"rotationY": -36.0,
							"rotationZ": -8.0,
							"foliageWaveSpecial": 3, "faces": {
								"north": { "texture": "#normal1-6", "uv": [ 0.0, 0.0, 2.5, 0.5 ], "enabled": false },
								"east": { "texture": "#normal1-6", "uv": [ 0.0, 0.0, 1.5, 0.5 ], "enabled": false },
								"south": { "texture": "#normal1-6", "uv": [ 0.0, 0.0, 2.5, 0.5 ], "enabled": false },
								"west": { "texture": "#normal1-6", "uv": [ 0.0, 0.0, 1.5, 0.5 ], "enabled": false },
								"up": { "texture": "#normal1-6", "uv": [ 13.5, 13.5, 16.0, 15.0 ] },
								"down": { "texture": "#normal1-6", "uv": [ 0.0, 0.0, 2.5, 1.5 ], "enabled": false }
							}
						}
					]
				},
				{
					"name": "stemdown15",
					"from": [ 4.8, -0.3, -4.1 ], 
					"to": [ 5.1, 3.7, -3.8 ], 
					"rotationOrigin": [ 5.0, -0.3, -4.0 ],
					"rotationX": 1.0,
					"rotationY": -42.0,
					"foliageWaveSpecial": 3, "faces": {
						"north": { "texture": "#normal1-6", "uv": [ 0.0, 0.0, 0.5, 4.0 ] },
						"east": { "texture": "#normal1-6", "uv": [ 0.0, 0.0, 0.5, 4.0 ] },
						"south": { "texture": "#normal1-6", "uv": [ 0.0, 0.0, 0.5, 4.0 ] },
						"west": { "texture": "#normal1-6", "uv": [ 0.0, 0.0, 0.5, 4.0 ] },
						"up": { "texture": "#normal1-6", "uv": [ 0.0, 0.0, 0.5, 0.5 ] },
						"down": { "texture": "#normal1-6", "uv": [ 0.5, 14.5, 1.0, 15.0 ] }
					},
					"children": [
						{
							"name": "Leaf22",
							"from": [ -1.1, 2.2, -1.2 ], 
							"to": [ 1.4, 2.2, 0.3 ], 
							"rotationOrigin": [ 0.2, 2.2, 0.3 ],
							"rotationX": 17.0,
							"rotationZ": 19.0,
							"foliageWaveSpecial": 3, "faces": {
								"north": { "texture": "#normal1-6", "uv": [ 0.0, 0.0, 2.5, 0.5 ], "enabled": false },
								"east": { "texture": "#normal1-6", "uv": [ 0.0, 0.0, 1.5, 0.5 ], "enabled": false },
								"south": { "texture": "#normal1-6", "uv": [ 0.0, 0.0, 2.5, 0.5 ], "enabled": false },
								"west": { "texture": "#normal1-6", "uv": [ 0.0, 0.0, 1.5, 0.5 ], "enabled": false },
								"up": { "texture": "#normal1-6", "uv": [ 13.5, 13.5, 16.0, 15.0 ] },
								"down": { "texture": "#normal1-6", "uv": [ 0.0, 0.0, 2.5, 1.5 ], "enabled": false }
							}
						},
						{
							"name": "Leaf23",
							"from": [ -1.0, 3.0, -1.4 ], 
							"to": [ 1.5, 3.0, 0.1 ], 
							"rotationOrigin": [ 0.2, 3.0, 0.1 ],
							"rotationX": 17.0,
							"rotationY": 39.0,
							"rotationZ": -3.0,
							"foliageWaveSpecial": 3, "faces": {
								"north": { "texture": "#normal1-6", "uv": [ 0.0, 0.0, 2.5, 0.5 ], "enabled": false },
								"east": { "texture": "#normal1-6", "uv": [ 0.0, 0.0, 1.5, 0.5 ], "enabled": false },
								"south": { "texture": "#normal1-6", "uv": [ 0.0, 0.0, 2.5, 0.5 ], "enabled": false },
								"west": { "texture": "#normal1-6", "uv": [ 0.0, 0.0, 1.5, 0.5 ], "enabled": false },
								"up": { "texture": "#normal1-6", "uv": [ 13.5, 13.5, 16.0, 15.0 ] },
								"down": { "texture": "#normal1-6", "uv": [ 0.0, 0.0, 2.5, 1.5 ], "enabled": false }
							}
						},
						{
							"name": "Leaf24",
							"from": [ -1.0, 1.4, -1.2 ], 
							"to": [ 1.5, 1.4, 0.3 ], 
							"rotationOrigin": [ 0.3, 1.4, 0.3 ],
							"rotationX": -14.0,
							"rotationY": -130.0,
							"foliageWaveSpecial": 3, "faces": {
								"north": { "texture": "#normal1-6", "uv": [ 0.0, 0.0, 2.5, 0.5 ], "enabled": false },
								"east": { "texture": "#normal1-6", "uv": [ 0.0, 0.0, 1.5, 0.5 ], "enabled": false },
								"south": { "texture": "#normal1-6", "uv": [ 0.0, 0.0, 2.5, 0.5 ], "enabled": false },
								"west": { "texture": "#normal1-6", "uv": [ 0.0, 0.0, 1.5, 0.5 ], "enabled": false },
								"up": { "texture": "#normal1-6", "uv": [ 13.5, 13.5, 16.0, 15.0 ] },
								"down": { "texture": "#normal1-6", "uv": [ 0.0, 0.0, 2.5, 1.5 ], "enabled": false }
							}
						},
						{
							"name": "Leaf25",
							"from": [ -1.3, 2.4, -1.3 ], 
							"to": [ 1.2, 2.4, 0.2 ], 
							"rotationOrigin": [ 0.0, 2.4, 0.2 ],
							"rotationX": -14.0,
							"rotationY": 163.0,
							"foliageWaveSpecial": 3, "faces": {
								"north": { "texture": "#normal1-6", "uv": [ 0.0, 0.0, 2.5, 0.5 ], "enabled": false },
								"east": { "texture": "#normal1-6", "uv": [ 0.0, 0.0, 1.5, 0.5 ], "enabled": false },
								"south": { "texture": "#normal1-6", "uv": [ 0.0, 0.0, 2.5, 0.5 ], "enabled": false },
								"west": { "texture": "#normal1-6", "uv": [ 0.0, 0.0, 1.5, 0.5 ], "enabled": false },
								"up": { "texture": "#normal1-6", "uv": [ 13.5, 13.5, 16.0, 15.0 ] },
								"down": { "texture": "#normal1-6", "uv": [ 0.0, 0.0, 2.5, 1.5 ], "enabled": false }
							}
						},
						{
							"name": "Leaf26",
							"from": [ -1.1, 3.7, -1.1 ], 
							"to": [ 1.4, 3.7, 0.4 ], 
							"rotationOrigin": [ 0.2, 3.7, 0.4 ],
							"rotationX": -19.0,
							"rotationY": -135.0,
							"rotationZ": -36.0,
							"foliageWaveSpecial": 3, "faces": {
								"north": { "texture": "#normal1-6", "uv": [ 0.0, 0.0, 2.5, 0.5 ], "enabled": false },
								"east": { "texture": "#normal1-6", "uv": [ 0.0, 0.0, 1.5, 0.5 ], "enabled": false },
								"south": { "texture": "#normal1-6", "uv": [ 0.0, 0.0, 2.5, 0.5 ], "enabled": false },
								"west": { "texture": "#normal1-6", "uv": [ 0.0, 0.0, 1.5, 0.5 ], "enabled": false },
								"up": { "texture": "#normal1-6", "uv": [ 13.5, 13.5, 16.0, 15.0 ] },
								"down": { "texture": "#normal1-6", "uv": [ 0.0, 0.0, 2.5, 1.5 ], "enabled": false }
							}
						}
					]
				},
				{
					"name": "stemdown28",
					"from": [ 4.8, -0.3, 4.8 ], 
					"to": [ 5.1, 3.7, 5.1 ], 
					"rotationOrigin": [ 5.0, -0.3, 5.0 ],
					"rotationX": -3.0,
					"rotationY": -39.0,
					"rotationZ": -2.0,
					"foliageWaveSpecial": 3, "faces": {
						"north": { "texture": "#normal1-6", "uv": [ 0.0, 0.0, 0.5, 4.0 ] },
						"east": { "texture": "#normal1-6", "uv": [ 0.0, 0.0, 0.5, 4.0 ] },
						"south": { "texture": "#normal1-6", "uv": [ 0.0, 0.0, 0.5, 4.0 ] },
						"west": { "texture": "#normal1-6", "uv": [ 0.0, 0.0, 0.5, 4.0 ] },
						"up": { "texture": "#normal1-6", "uv": [ 0.0, 1.0, 0.5, 1.5 ] },
						"down": { "texture": "#normal1-6", "uv": [ 0.5, 14.5, 1.0, 15.0 ] }
					},
					"children": [
						{
							"name": "Leaf35",
							"from": [ -1.0, 1.0, -1.3 ], 
							"to": [ 1.5, 1.0, 0.2 ], 
							"rotationOrigin": [ 0.5, 1.0, 0.2 ],
							"rotationX": 14.0,
							"rotationZ": -8.0,
							"foliageWaveSpecial": 3, "faces": {
								"north": { "texture": "#normal1-6", "uv": [ 0.0, 4.0, 2.5, 4.5 ], "enabled": false },
								"east": { "texture": "#normal1-6", "uv": [ 0.0, 0.0, 1.5, 0.5 ], "enabled": false },
								"south": { "texture": "#normal1-6", "uv": [ 0.0, 0.0, 2.5, 0.5 ], "enabled": false },
								"west": { "texture": "#normal1-6", "uv": [ 0.0, 0.0, 1.5, 0.5 ], "enabled": false },
								"up": { "texture": "#normal1-6", "uv": [ 13.5, 13.5, 16.0, 15.0 ] },
								"down": { "texture": "#normal1-6", "uv": [ 0.0, 0.0, 2.5, 1.5 ], "enabled": false }
							}
						},
						{
							"name": "Leaf36",
							"from": [ -1.5, 2.0, -1.3 ], 
							"to": [ 1.0, 2.0, 0.2 ], 
							"rotationOrigin": [ 0.0, 2.0, 0.2 ],
							"rotationX": 25.0,
							"rotationY": 3.0,
							"rotationZ": -6.0,
							"foliageWaveSpecial": 3, "faces": {
								"north": { "texture": "#normal1-6", "uv": [ 0.0, 0.0, 2.5, 0.5 ], "enabled": false },
								"east": { "texture": "#normal1-6", "uv": [ 0.0, 0.0, 1.5, 0.5 ], "enabled": false },
								"south": { "texture": "#normal1-6", "uv": [ 0.0, 0.0, 2.5, 0.5 ], "enabled": false },
								"west": { "texture": "#normal1-6", "uv": [ 0.0, 0.0, 1.5, 0.5 ], "enabled": false },
								"up": { "texture": "#normal1-6", "uv": [ 13.5, 13.5, 16.0, 15.0 ] },
								"down": { "texture": "#normal1-6", "uv": [ 0.0, 0.0, 2.5, 1.5 ], "enabled": false }
							}
						},
						{
							"name": "Leaf37",
							"from": [ -1.5, 2.0, -1.3 ], 
							"to": [ 1.0, 2.0, 0.2 ], 
							"rotationOrigin": [ 0.0, 2.0, 0.2 ],
							"rotationX": -25.0,
							"rotationY": -163.0,
							"foliageWaveSpecial": 3, "faces": {
								"north": { "texture": "#normal1-6", "uv": [ 0.0, 0.0, 2.5, 0.5 ], "enabled": false },
								"east": { "texture": "#normal1-6", "uv": [ 0.0, 0.0, 1.5, 0.5 ], "enabled": false },
								"south": { "texture": "#normal1-6", "uv": [ 0.0, 0.0, 2.5, 0.5 ], "enabled": false },
								"west": { "texture": "#normal1-6", "uv": [ 0.0, 0.0, 1.5, 0.5 ], "enabled": false },
								"up": { "texture": "#normal1-6", "uv": [ 13.5, 13.5, 16.0, 15.0 ] },
								"down": { "texture": "#normal1-6", "uv": [ 0.0, 0.0, 2.5, 1.5 ], "enabled": false }
							}
						},
						{
							"name": "Leaf38",
							"from": [ -1.1, 3.2, -1.4 ], 
							"to": [ 1.4, 3.2, 0.1 ], 
							"rotationOrigin": [ 0.2, 3.2, 0.1 ],
							"rotationX": -6.0,
							"rotationY": 114.0,
							"rotationZ": -8.0,
							"foliageWaveSpecial": 3, "faces": {
								"north": { "texture": "#normal1-6", "uv": [ 0.0, 0.0, 2.5, 0.5 ], "enabled": false },
								"east": { "texture": "#normal1-6", "uv": [ 0.0, 0.0, 1.5, 0.5 ], "enabled": false },
								"south": { "texture": "#normal1-6", "uv": [ 0.0, 0.0, 2.5, 0.5 ], "enabled": false },
								"west": { "texture": "#normal1-6", "uv": [ 0.0, 0.0, 1.5, 0.5 ], "enabled": false },
								"up": { "texture": "#normal1-6", "uv": [ 13.5, 13.5, 16.0, 15.0 ] },
								"down": { "texture": "#normal1-6", "uv": [ 0.0, 0.0, 2.5, 1.5 ], "enabled": false }
							}
						},
						{
							"name": "Leaf40",
							"from": [ -1.3, 3.8, -1.4 ], 
							"to": [ 1.2, 3.8, 0.1 ], 
							"rotationOrigin": [ 0.2, 3.8, 0.1 ],
							"rotationX": 44.0,
							"rotationY": 3.0,
							"rotationZ": 3.0,
							"foliageWaveSpecial": 3, "faces": {
								"north": { "texture": "#normal1-6", "uv": [ 0.0, 0.0, 2.5, 0.5 ], "enabled": false },
								"east": { "texture": "#normal1-6", "uv": [ 0.0, 0.0, 1.5, 0.5 ], "enabled": false },
								"south": { "texture": "#normal1-6", "uv": [ 0.0, 0.0, 2.5, 0.5 ], "enabled": false },
								"west": { "texture": "#normal1-6", "uv": [ 0.0, 0.0, 1.5, 0.5 ], "enabled": false },
								"up": { "texture": "#normal1-6", "uv": [ 13.5, 13.5, 16.0, 15.0 ] },
								"down": { "texture": "#normal1-6", "uv": [ 0.0, 0.0, 2.5, 1.5 ], "enabled": false }
							}
						}
					]
				},
				{
					"name": "stemdown41",
					"from": [ -4.2, -0.3, 4.9 ], 
					"to": [ -3.9, 3.7, 5.2 ], 
					"rotationOrigin": [ -4.0, -0.3, 5.0 ],
					"rotationX": -2.0,
					"rotationY": -30.0,
					"rotationZ": 1.0,
					"foliageWaveSpecial": 3, "faces": {
						"north": { "texture": "#normal1-6", "uv": [ 0.0, 0.0, 0.5, 4.0 ] },
						"east": { "texture": "#normal1-6", "uv": [ 0.0, 0.0, 0.5, 4.0 ] },
						"south": { "texture": "#normal1-6", "uv": [ 0.0, 0.0, 0.5, 4.0 ] },
						"west": { "texture": "#normal1-6", "uv": [ 0.0, 0.0, 0.5, 4.0 ] },
						"up": { "texture": "#normal1-6", "uv": [ 0.0, 0.0, 0.5, 0.5 ] },
						"down": { "texture": "#normal1-6", "uv": [ 0.5, 14.5, 1.0, 15.0 ] }
					},
					"children": [
						{
							"name": "Leaf48",
							"from": [ -1.7, 2.0, -1.3 ], 
							"to": [ 0.8, 2.0, 0.2 ], 
							"rotationOrigin": [ 0.1, 2.0, 0.2 ],
							"rotationX": 19.0,
							"rotationY": -36.0,
							"rotationZ": -14.0,
							"foliageWaveSpecial": 3, "faces": {
								"north": { "texture": "#normal1-6", "uv": [ 0.0, 0.0, 2.5, 0.5 ], "enabled": false },
								"east": { "texture": "#normal1-6", "uv": [ 0.0, 0.0, 1.5, 0.5 ], "enabled": false },
								"south": { "texture": "#normal1-6", "uv": [ 0.0, 0.0, 2.5, 0.5 ], "enabled": false },
								"west": { "texture": "#normal1-6", "uv": [ 0.0, 0.0, 1.5, 0.5 ], "enabled": false },
								"up": { "texture": "#normal1-6", "uv": [ 10.5, 12.5, 13.0, 14.0 ] },
								"down": { "texture": "#normal1-6", "uv": [ 0.0, 0.0, 2.5, 1.5 ], "enabled": false }
							}
						},
						{
							"name": "Leaf49",
							"from": [ -0.9, 3.0, -1.2 ], 
							"to": [ 1.6, 3.0, 0.3 ], 
							"rotationOrigin": [ 0.3, 3.0, 0.3 ],
							"rotationX": 17.0,
							"rotationY": 64.0,
							"rotationZ": -3.0,
							"foliageWaveSpecial": 3, "faces": {
								"north": { "texture": "#normal1-6", "uv": [ 0.0, 0.0, 2.5, 0.5 ], "enabled": false },
								"east": { "texture": "#normal1-6", "uv": [ 0.0, 0.0, 1.5, 0.5 ], "enabled": false },
								"south": { "texture": "#normal1-6", "uv": [ 0.0, 0.0, 2.5, 0.5 ], "enabled": false },
								"west": { "texture": "#normal1-6", "uv": [ 0.0, 0.0, 1.5, 0.5 ], "enabled": false },
								"up": { "texture": "#normal1-6", "uv": [ 13.5, 13.5, 16.0, 15.0 ] },
								"down": { "texture": "#normal1-6", "uv": [ 0.0, 0.0, 2.5, 1.5 ], "enabled": false }
							}
						},
						{
							"name": "Leaf50",
							"from": [ -1.3, 1.6, -1.2 ], 
							"to": [ 1.2, 1.6, 0.3 ], 
							"rotationOrigin": [ 0.0, 1.6, 0.3 ],
							"rotationX": -22.0,
							"rotationY": -180.0,
							"foliageWaveSpecial": 3, "faces": {
								"north": { "texture": "#normal1-6", "uv": [ 0.0, 0.0, 2.5, 0.5 ], "enabled": false },
								"east": { "texture": "#normal1-6", "uv": [ 0.0, 0.0, 1.5, 0.5 ], "enabled": false },
								"south": { "texture": "#normal1-6", "uv": [ 0.0, 0.0, 2.5, 0.5 ], "enabled": false },
								"west": { "texture": "#normal1-6", "uv": [ 0.0, 0.0, 1.5, 0.5 ], "enabled": false },
								"up": { "texture": "#normal1-6", "uv": [ 13.5, 14.5, 16.0, 16.0 ], "rotation": 180 },
								"down": { "texture": "#normal1-6", "uv": [ 0.0, 0.0, 2.5, 1.5 ], "enabled": false }
							}
						},
						{
							"name": "Leaf53",
							"from": [ -1.0, 3.6, -1.1 ], 
							"to": [ 1.5, 3.6, 0.4 ], 
							"rotationOrigin": [ 0.1, 3.6, 0.4 ],
							"rotationX": 22.0,
							"rotationY": -89.0,
							"rotationZ": 19.0,
							"foliageWaveSpecial": 3, "faces": {
								"north": { "texture": "#normal1-6", "uv": [ 0.0, 0.0, 2.5, 0.5 ], "enabled": false },
								"east": { "texture": "#normal1-6", "uv": [ 0.0, 0.0, 1.5, 0.5 ], "enabled": false },
								"south": { "texture": "#normal1-6", "uv": [ 0.0, 0.0, 2.5, 0.5 ], "enabled": false },
								"west": { "texture": "#normal1-6", "uv": [ 0.0, 0.0, 1.5, 0.5 ], "enabled": false },
								"up": { "texture": "#normal1-6", "uv": [ 13.5, 13.5, 16.0, 15.0 ] },
								"down": { "texture": "#normal1-6", "uv": [ 0.0, 0.0, 2.5, 1.5 ], "enabled": false }
							}
						}
					]
				}
			]
		}
	]}